{
  "lastIncludedIndex": 160,
  "lastIncludedTerm": 23,
  "log": [
    {
      "Command": "command 771",
      "Term": 23
    },
    {
      "Command": "command 229",
      "Term": 23
    },
    {
      "Command": "command 456",
      "Term": 23
    },
    {
      "Command": "command 471",
      "Term": 23
    },
    {
      "Command": "command 835",
      "Term": 23
    },
    {
      "Command": "command 510",
      "Term": 23
    },
    {
      "Command": "command 68",
      "Term": 23
    },
    {
      "Command": "command 122",
      "Term": 23
    },
    {
      "Command": "command 385",
      "Term": 23
    },
    {
      "Command": "command 200",
      "Term": 23
    },
    {
      "Command": "command 407",
      "Term": 23
    },
    {
      "Command": "command 824",
      "Term": 23
    },
    {
      "Command": "command 587",
      "Term": 23
    },
    {
      "Command": "command 677",
      "Term": 23
    },
    {
      "Command": "command 964",
      "Term": 23
    },
    {
      "Command": "command 730",
      "Term": 23
    },
    {
      "Command": "command 294",
      "Term": 23
    },
    {
      "Command": "command 388",
      "Term": 23
    },
    {
      "Command": "command 187",
      "Term": 23
    },
    {
      "Command": "command 333",
      "Term": 23
    },
    {
      "Command": "command 378",
      "Term": 23
    },
    {
      "Command": "command 656",
      "Term": 23
    },
    {
      "Command": "command 7",
      "Term": 23
    },
    {
      "Command": "command 326",
      "Term": 23
    },
    {
      "Command": "command 544",
      "Term": 23
    },
    {
      "Command": "command 801",
      "Term": 23
    },
    {
      "Command": "command 533",
      "Term": 23
    },
    {
      "Command": "command 964",
      "Term": 23
    },
    {
      "Command": "command 662",
      "Term": 23
    },
    {
      "Command": "command 697",
      "Term": 23
    },
    {
      "Command": "command 615",
      "Term": 23
    },
    {
      "Command": "command 264",
      "Term": 23
    }
  ]
}