{
  "lastIncludedIndex": 32,
  "lastIncludedTerm": 1,
  "log": [
    {
      "Command": "command 910",
      "Term": 1
    },
    {
      "Command": "command 141",
      "Term": 1
    },
    {
      "Command": "command 839",
      "Term": 1
    },
    {
      "Command": "command 943",
      "Term": 1
    },
    {
      "Command": "command 250",
      "Term": 1
    },
    {
      "Command": "command 195",
      "Term": 1
    },
    {
      "Command": "command 242",
      "Term": 1
    },
    {
      "Command": "command 428",
      "Term": 1
    },
    {
      "Command": "command 554",
      "Term": 1
    },
    {
      "Command": "command 826",
      "Term": 1
    },
    {
      "Command": "command 894",
      "Term": 1
    },
    {
      "Command": "command 685",
      "Term": 1
    },
    {
      "Command": "command 477",
      "Term": 1
    },
    {
      "Command": "command 591",
      "Term": 1
    },
    {
      "Command": "command 982",
      "Term": 1
    },
    {
      "Command": "command 887",
      "Term": 1
    },
    {
      "Command": "command 620",
      "Term": 1
    },
    {
      "Command": "command 301",
      "Term": 1
    },
    {
      "Command": "command 666",
      "Term": 1
    },
    {
      "Command": "command 619",
      "Term": 1
    },
    {
      "Command": "command 219",
      "Term": 1
    },
    {
      "Command": "command 563",
      "Term": 1
    },
    {
      "Command": "command 863",
      "Term": 1
    },
    {
      "Command": "command 395",
      "Term": 1
    },
    {
      "Command": "command 13",
      "Term": 1
    },
    {
      "Command": "command 822",
      "Term": 1
    },
    {
      "Command": "command 612",
      "Term": 1
    },
    {
      "Command": "command 233",
      "Term": 1
    },
    {
      "Command": "command 849",
      "Term": 1
    },
    {
      "Command": "command 856",
      "Term": 1
    },
    {
      "Command": "command 869",
      "Term": 1
    },
    {
      "Command": "command 471",
      "Term": 1
    }
  ]
}