{
  "lastIncludedIndex": 64,
  "lastIncludedTerm": 19,
  "log": [
    {
      "Command": "command 811",
      "Term": 1
    },
    {
      "Command": "command 149",
      "Term": 1
    },
    {
      "Command": "command 33",
      "Term": 1
    },
    {
      "Command": "command 836",
      "Term": 1
    },
    {
      "Command": "command 372",
      "Term": 1
    },
    {
      "Command": "command 210",
      "Term": 1
    },
    {
      "Command": "command 425",
      "Term": 1
    },
    {
      "Command": "command 122",
      "Term": 1
    },
    {
      "Command": "command 894",
      "Term": 1
    },
    {
      "Command": "command 36",
      "Term": 1
    },
    {
      "Command": "command 916",
      "Term": 1
    },
    {
      "Command": "command 177",
      "Term": 1
    },
    {
      "Command": "command 283",
      "Term": 1
    },
    {
      "Command": "command 517",
      "Term": 1
    },
    {
      "Command": "command 698",
      "Term": 1
    },
    {
      "Command": "command 376",
      "Term": 1
    },
    {
      "Command": "command 14",
      "Term": 1
    },
    {
      "Command": "command 992",
      "Term": 1
    },
    {
      "Command": "command 779",
      "Term": 1
    },
    {
      "Command": "command 575",
      "Term": 1
    },
    {
      "Command": "command 971",
      "Term": 1
    },
    {
      "Command": "command 397",
      "Term": 1
    },
    {
      "Command": "command 789",
      "Term": 19
    },
    {
      "Command": "command 841",
      "Term": 19
    },
    {
      "Command": "command 290",
      "Term": 19
    },
    {
      "Command": "command 644",
      "Term": 19
    },
    {
      "Command": "command 511",
      "Term": 19
    },
    {
      "Command": "command 238",
      "Term": 19
    },
    {
      "Command": "command 827",
      "Term": 19
    },
    {
      "Command": "command 658",
      "Term": 19
    },
    {
      "Command": "command 495",
      "Term": 19
    },
    {
      "Command": "command 198",
      "Term": 19
    }
  ]
}