{
  "lastIncludedIndex": 96,
  "lastIncludedTerm": 11,
  "log": [
    {
      "Command": "command 578",
      "Term": 11
    },
    {
      "Command": "command 443",
      "Term": 11
    },
    {
      "Command": "command 598",
      "Term": 11
    },
    {
      "Command": "command 924",
      "Term": 11
    },
    {
      "Command": "command 517",
      "Term": 11
    },
    {
      "Command": "command 638",
      "Term": 11
    },
    {
      "Command": "command 756",
      "Term": 11
    },
    {
      "Command": "command 197",
      "Term": 11
    },
    {
      "Command": "command 758",
      "Term": 11
    },
    {
      "Command": "command 922",
      "Term": 11
    },
    {
      "Command": "command 246",
      "Term": 11
    },
    {
      "Command": "command 605",
      "Term": 11
    },
    {
      "Command": "command 391",
      "Term": 11
    },
    {
      "Command": "command 318",
      "Term": 11
    },
    {
      "Command": "command 191",
      "Term": 11
    },
    {
      "Command": "command 917",
      "Term": 11
    },
    {
      "Command": "command 100",
      "Term": 11
    },
    {
      "Command": "command 1",
      "Term": 11
    },
    {
      "Command": "command 865",
      "Term": 11
    },
    {
      "Command": "command 334",
      "Term": 11
    },
    {
      "Command": "command 361",
      "Term": 11
    },
    {
      "Command": "command 139",
      "Term": 11
    },
    {
      "Command": "command 444",
      "Term": 11
    },
    {
      "Command": "command 197",
      "Term": 11
    },
    {
      "Command": "command 418",
      "Term": 11
    },
    {
      "Command": "command 634",
      "Term": 11
    },
    {
      "Command": "command 785",
      "Term": 11
    },
    {
      "Command": "command 219",
      "Term": 11
    },
    {
      "Command": "command 155",
      "Term": 11
    },
    {
      "Command": "command 817",
      "Term": 11
    },
    {
      "Command": "command 272",
      "Term": 11
    },
    {
      "Command": "command 794",
      "Term": 11
    }
  ]
}